debugrecorder/__init__.py
debugrecorder/debug_recorder.py
debugrecorder/test.py
debugrecorder-0.1.0.dist-info/licenses/LICENSE
debugrecorder-0.1.0.dist-info/METADATA
debugrecorder-0.1.0.dist-info/WHEEL
debugrecorder-0.1.0.dist-info/top_level.txt
debugrecorder-0.1.0.dist-info/RECORD
