Metadata-Version: 2.4
Name: debugrecorder
Version: 0.1.0
Summary: A Python debug session recorder that captures line events and variable states
Home-page: https://github.com/mdrazak2001/debugrecorder
Author: Mohammed Razak
Author-email: mohammedrazak2001@gmail.com
Classifier: Development Status :: 3 - Alpha
Classifier: Intended Audience :: Developers
Classifier: License :: OSI Approved :: MIT License
Classifier: Programming Language :: Python :: 3
Classifier: Programming Language :: Python :: 3.6
Classifier: Programming Language :: Python :: 3.7
Classifier: Programming Language :: Python :: 3.8
Classifier: Programming Language :: Python :: 3.9
Requires-Python: >=3.6
License-File: LICENSE
Dynamic: author
Dynamic: author-email
Dynamic: classifier
Dynamic: home-page
Dynamic: license-file
Dynamic: requires-python
Dynamic: summary
